LICENSE
MANIFEST
MANIFEST.in
README.md
README.rst
change_log.txt
requirements.txt
setup.cfg
setup.py
alg/__init__.py
alg/sort_function.py
alg.egg-info/PKG-INFO
alg.egg-info/SOURCES.txt
alg.egg-info/dependency_links.txt
alg.egg-info/not-zip-safe
alg.egg-info/requires.txt
alg.egg-info/top_level.txt